threemystic_cloud_client/__main__.py
threemystic_cloud_client/__version__.py
threemystic_cloud_client/cloud_client.py
threemystic_cloud_client/cli/__init__.py
threemystic_cloud_client/cli/actions/action_generate/__init__.py
threemystic_cloud_client/cli/actions/action_test/__init__.py
threemystic_cloud_client/cli/actions/action_token/__init__.py
threemystic_cloud_client/cli/actions/base_class/base.py
threemystic_cloud_client/cli/actions/config/__init__.py
threemystic_cloud_client/cloud_providers/aws/__init__.py
threemystic_cloud_client/cloud_providers/aws/action_generate/step_1.py
threemystic_cloud_client/cloud_providers/aws/action_generate/base_class/base.py
threemystic_cloud_client/cloud_providers/aws/action_test/step_1.py
threemystic_cloud_client/cloud_providers/aws/action_test/step_2.py
threemystic_cloud_client/cloud_providers/aws/action_test/base_class/base.py
threemystic_cloud_client/cloud_providers/aws/action_token/step_1.py
threemystic_cloud_client/cloud_providers/aws/action_token/base_class/base.py
threemystic_cloud_client/cloud_providers/aws/base_class/base.py
threemystic_cloud_client/cloud_providers/aws/client/auto_client.py
threemystic_cloud_client/cloud_providers/aws/client/sso.py
threemystic_cloud_client/cloud_providers/aws/client/base_class/base.py
threemystic_cloud_client/cloud_providers/aws/config/step_1.py
threemystic_cloud_client/cloud_providers/aws/config/step_2.py
threemystic_cloud_client/cloud_providers/aws/config/base_class/base.py
threemystic_cloud_client/cloud_providers/azure/__init__.py
threemystic_cloud_client/cloud_providers/azure/action_test/step_1.py
threemystic_cloud_client/cloud_providers/azure/action_test/base_class/base.py
threemystic_cloud_client/cloud_providers/azure/action_token/step_1.py
threemystic_cloud_client/cloud_providers/azure/action_token/base_class/base.py
threemystic_cloud_client/cloud_providers/azure/base_class/base.py
threemystic_cloud_client/cloud_providers/azure/client/auto_client.py
threemystic_cloud_client-0.1.64.dist-info/METADATA
threemystic_cloud_client-0.1.64.dist-info/WHEEL
threemystic_cloud_client-0.1.64.dist-info/entry_points.txt
threemystic_cloud_client-0.1.64.dist-info/licenses/LICENSE
threemystic_cloud_client-0.1.64.dist-info/RECORD
