Metadata-Version: 2.1
Name: threemystic-cloud-client
Version: 0.1.64
Summary: A tool to help facilitate the communication with various cloud providers
Project-URL: Homepage, https://github.com/3MysticApes/3mystic_cloud_client
Project-URL: Bug Tracker, https://github.com/3MysticApes/3mystic_cloud_client/issues
Author: Ron Truex
License-Expression: MIT
License-File: LICENSE
Classifier: License :: OSI Approved :: MIT License
Classifier: Natural Language :: English
Classifier: Operating System :: OS Independent
Classifier: Programming Language :: Python :: 3.8
Classifier: Programming Language :: Python :: 3.9
Classifier: Programming Language :: Python :: 3.10
Classifier: Programming Language :: Python :: 3.11
Classifier: Programming Language :: Python :: Implementation :: CPython
Classifier: Programming Language :: Python :: Implementation :: PyPy
Requires-Python: >=3.8
Requires-Dist: azure-cli>=2.50.0
Requires-Dist: azure-common>=1.1.28
Requires-Dist: azure-identity>=1.13.0
Requires-Dist: azure-mgmt-managementgroups>=1.0.0
Requires-Dist: azure-mgmt-resourcegraph>=8.0.0
Requires-Dist: azure-mgmt-sql>=3.0.1
Requires-Dist: azure-mgmt-subscription>=3.1.1
Requires-Dist: boto3>=1.28.15
Requires-Dist: botocore>=1.31.16
Requires-Dist: colorama; platform_system == 'Windows'
Requires-Dist: cryptography>=41.0.1
Requires-Dist: polling2>=0.5.0
Requires-Dist: pyjwt>=2.7.0
Requires-Dist: pyopenssl>=22.1.0
Requires-Dist: threemystic-common>=0.1.17
Requires-Dist: typing-extensions>=4.4.0
